mpi_cbs/huscy/mpicbs_project_consents/__init__.py
mpi_cbs/huscy/mpicbs_project_consents/apps.py
mpi_cbs/huscy/mpicbs_project_consents/urls.py
mpi_cbs/huscy/mpicbs_project_consents/views.py
mpi_cbs/huscy/mpicbs_project_consents/templates/mpicbs_project_consents/signed_consents.html
mpi_cbs.huscy.mpicbs_project_consents-0.3.1a3.dist-info/METADATA
mpi_cbs.huscy.mpicbs_project_consents-0.3.1a3.dist-info/WHEEL
mpi_cbs.huscy.mpicbs_project_consents-0.3.1a3.dist-info/top_level.txt
mpi_cbs.huscy.mpicbs_project_consents-0.3.1a3.dist-info/RECORD
